Workbook

Sheet Summary
A1: DSA Questions Summary - Complete Edition (450 Questions)
A3: Total Questions: | B3: =COUNTA('DSA Questions'!A2:A10000) -> 450
A5: By Difficulty:
A6: Easy: | B6: =COUNTIF('DSA Questions'!E:E,"Easy") -> 123
A7: Medium: | B7: =COUNTIF('DSA Questions'!E:E,"Medium") -> 236
A8: Hard: | B8: =COUNTIF('DSA Questions'!E:E,"Hard") -> 91
A10: By Category:
A11: Array: | B11: =COUNTIF('DSA Questions'!D:D,"Array") -> 30
A12: Backtracking: | B12: =COUNTIF('DSA Questions'!D:D,"Backtracking") -> 19
A13: Binary Search: | B13: =COUNTIF('DSA Questions'!D:D,"Binary Search") -> 21
A14: Binary Tree: | B14: =COUNTIF('DSA Questions'!D:D,"Binary Tree") -> 29
A15: Bit Manipulation: | B15: =COUNTIF('DSA Questions'!D:D,"Bit Manipulation") -> 18
A16: Design: | B16: =COUNTIF('DSA Questions'!D:D,"Design") -> 19
A17: Dynamic Programming: | B17: =COUNTIF('DSA Questions'!D:D,"Dynamic Programming") -> 39
A18: Graph: | B18: =COUNTIF('DSA Questions'!D:D,"Graph") -> 21
A19: Greedy: | B19: =COUNTIF('DSA Questions'!D:D,"Greedy") -> 16
A20: Hash Map: | B20: =COUNTIF('DSA Questions'!D:D,"Hash Map") -> 54
A21: Heap: | B21: =COUNTIF('DSA Questions'!D:D,"Heap") -> 17
A22: Linked List: | B22: =COUNTIF('DSA Questions'!D:D,"Linked List") -> 21
A23: Math: | B23: =COUNTIF('DSA Questions'!D:D,"Math") -> 24
A24: Queue: | B24: =COUNTIF('DSA Questions'!D:D,"Queue") -> 7
A25: Sliding Window: | B25: =COUNTIF('DSA Questions'!D:D,"Sliding Window") -> 15
A26: Sorting: | B26: =COUNTIF('DSA Questions'!D:D,"Sorting") -> 16
A27: Stack: | B27: =COUNTIF('DSA Questions'!D:D,"Stack") -> 19
A28: String: | B28: =COUNTIF('DSA Questions'!D:D,"String") -> 27
A29: Trie: | B29: =COUNTIF('DSA Questions'!D:D,"Trie") -> 9
A30: Two Pointers: | B30: =COUNTIF('DSA Questions'!D:D,"Two Pointers") -> 18
A31: Union Find: | B31: =COUNTIF('DSA Questions'!D:D,"Union Find") -> 11

Sheet DSA Questions
A1: Questions | B1: Short Description | C1: Full Problem Statement | D1: Category | E1: Difficulty | F1: Status
A2: Two Sum | B2: Find two numbers in array that add up to target value | C2: Given an array of integers nums and an integer target, return indices of the two numbers such that they add up to target. You may assume that each input would have exactly one solution, and you may not use the same element twice. You can return the answer in any order. Example: nums = [2,7,11,15], target = 9, Output: [0,1] because nums[0] + nums[1] = 2 + 7 = 9 | D2: Array | E2: Easy | F2: Completed
A3: Best Time to Buy and Sell Stock | B3: Find maximum profit from single buy and sell transaction | C3: You are given an array prices where prices[i] is the price of a given stock on the ith day. You want to maximize your profit by choosing a single day to buy one stock and choosing a different day in the future to sell that stock. Return the maximum profit you can achieve from this transaction. If you cannot achieve any profit, return 0. Example: Input: prices = [7,1,5,3,6,4], Output: 5 (buy on day 2 at price 1 and sell on day 5 at price 6, profit = 6-1 = 5) | D3: Array | E3: Easy
A4: Contains Duplicate | B4: Check if any value appears at least twice in array | C4: Given an integer array nums, return true if any value appears at least twice in the array, and return false if every element is distinct. Example: Input: nums = [1,2,3,1], Output: true. Input: nums = [1,2,3,4], Output: false. Can be solved using hash set in O(n) time. | D4: Array | E4: Easy
A5: Maximum Subarray (Kadane) | B5: Find contiguous subarray with largest sum | C5: Problem: Maximum Subarray (Kadane). Find contiguous subarray with largest sum. This is a Easy level problem in the Array category. Approach: Analyze the problem requirements, identify the appropriate data structure and algorithm, implement the solution efficiently considering time and space complexity. Test with various edge cases including empty inputs, single elements, and large datasets. | D5: Array | E5: Easy
A6: Move Zeroes | B6: Move all zeros to end while maintaining relative order | C6: Problem: Move Zeroes. Move all zeros to end while maintaining relative order. This is a Easy level problem in the Array category. Approach: Analyze the problem requirements, identify the appropriate data structure and algorithm, implement the solution efficiently considering time and space complexity. Test with various edge cases including empty inputs, single elements, and large datasets. | D6: Array | E6: Easy
A7: Plus One | B7: Increment large integer represented as array of digits | C7: Problem: Plus One. Increment large integer represented as array of digits. This is a Easy level problem in the Array category. Approach: Analyze the problem requirements, identify the appropriate data structure and algorithm, implement the solution efficiently considering time and space complexity. Test with various edge cases including empty inputs, single elements, and large datasets. | D7: Array | E7: Easy
A8: Remove Duplicates from Sorted Array | B8: Remove duplicates in-place from sorted array | C8: Problem: Remove Duplicates from Sorted Array. Remove duplicates in-place from sorted array. This is a Easy level problem in the Array category. Approach: Analyze the problem requirements, identify the appropriate data structure and algorithm, implement the solution efficiently considering time and space complexity. Test with various edge cases including empty inputs, single elements, and large datasets. | D8: Array | E8: Easy
A9: Merge Sorted Array | B9: Merge two sorted arrays into first array | C9: Problem: Merge Sorted Array. Merge two sorted arrays into first array. This is a Easy level problem in the Array category. Approach: Analyze the problem requirements, identify the appropriate data structure and algorithm, implement the solution efficiently considering time and space complexity. Test with various edge cases including empty inputs, single elements, and large datasets. | D9: Array | E9: Easy
A10: Pascal's Triangle | B10: Generate first n rows of Pascal's triangle | C10: Problem: Pascal's Triangle. Generate first n rows of Pascal's triangle. This is a Easy level problem in the Array category. Approach: Analyze the problem requirements, identify the appropriate data structure and algorithm, implement the solution efficiently considering time and space complexity. Test with various edge cases including empty inputs, single elements, and large datasets. | D10: Array | E10: Easy
A11: Single Number | B11: Find element that appears once while others appear twice | C11: Problem: Single Number. Find element that appears once while others appear twice. This is a Easy level problem in the Array category. Approach: Analyze the problem requirements, identify the appropriate data structure and algorithm, implement the solution efficiently considering time and space complexity. Test with various edge cases including empty inputs, single elements, and large datasets. | D11: Array | E11: Easy
A12: Product of Array Except Self | B12: Return array where each element is product of all others except self | C12: Given an integer array nums, return an array answer such that answer[i] is equal to the product of all the elements of nums except nums[i]. The product of any prefix or suffix of nums is guaranteed to fit in a 32-bit integer. You must write an algorithm that runs in O(n) time and without using the division operation. Example: Input: nums = [1,2,3,4], Output: [24,12,8,6] | D12: Array | E12: Medium
A13: 3Sum | B13: Find all unique triplets in array that sum to zero | C13: Given an integer array nums, return all the triplets [nums[i], nums[j], nums[k]] such that i != j, i != k, and j != k, and nums[i] + nums[j] + nums[k] == 0. Notice that the solution set must not contain duplicate triplets. Example: Input: nums = [-1,0,1,2,-1,-4], Output: [[-1,-1,2],[-1,0,1]]. Sort array first, then use two pointers for each element. | D13: Array | E13: Medium
A14: Container With Most Water | B14: Find two lines that form container holding most water | C14: You are given an integer array height of length n. There are n vertical lines drawn such that the two endpoints of the ith line are (i, 0) and (i, height[i]). Find two lines that together with the x-axis form a container, such that the container contains the most water. Return the maximum amount of water a container can store. Example: Input: height = [1,8,6,2,5,4,8,3,7], Output: 49. Use two pointers from both ends. | D14: Array | E14: Medium
... A451: Count of Range Sum | B451: Count range sums using hash map and merge sort | C451: Problem: Count of Range Sum. Count range sums using hash map and merge sort. This is a Hard level problem in the Hash Map category. Approach: Analyze the problem requirements, identify the appropriate data structure and algorithm, implement the solution efficiently considering time and space complexity. Test with various edge cases including empty inputs, single elements, and large datasets. | D451: Hash Map | E451: Hard
